org_mcp/__init__.py
org_mcp/cli.py
org_mcp/server.py
org_mcp-0.2.0.dist-info/METADATA
org_mcp-0.2.0.dist-info/WHEEL
org_mcp-0.2.0.dist-info/entry_points.txt
org_mcp-0.2.0.dist-info/top_level.txt
org_mcp-0.2.0.dist-info/RECORD
