Metadata-Version: 2.4
Name: org-mcp
Version: 0.2.0
Summary: A python-based MCP server for your local org mode files
Author-email: Andy Reagan <andy@andyreagan.com>
Requires-Python: >=3.11
Requires-Dist: mcp[cli]>=1.6.0
Requires-Dist: pytest>=8.3.5
